detadoc/__init__.py
detadoc/annotations.py
detadoc/bases.py
detadoc/enum.py
detadoc/helper.py
detadoc/models.py
detadoc/regex.py
detadoc-0.2.8.dist-info/WHEEL
detadoc-0.2.8.dist-info/METADATA
detadoc-0.2.8.dist-info/RECORD
