Metadata-Version: 2.1
Name: detadoc
Version: 0.2.8
Summary: 
Author: Daniel Arantes
Author-email: arantesdv@me.com
Requires-Python: >=3.9,<4.0
Classifier: Programming Language :: Python :: 3
Classifier: Programming Language :: Python :: 3.10
Classifier: Programming Language :: Python :: 3.9
Requires-Dist: Markdown (>=3.5.2,<4.0.0)
Requires-Dist: bcrypt (>=4.1.1,<5.0.0)
Requires-Dist: email-validator (>=2.1.0,<3.0.0)
Requires-Dist: httpx[http2] (>=0.26.0,<0.27.0)
Requires-Dist: hx-markup (>=0.2.2,<0.3.0)
Requires-Dist: requests (>=2.31.0,<3.0.0)
Requires-Dist: spacestar (>=0.3.1,<0.4.0)
